Metadata-Version: 2.1
Name: pfdicom
Version: 2.0.12
Summary: Base module for parsing DICOM files in the pf* family.
Home-page: https://github.com/FNNDSC/pfdicom
Author: FNNDSC
Author-email: dev@babymri.org
License: MIT
Platform: UNKNOWN
License-File: LICENSE
